Metadata-Version: 2.1
Name: ser2sock
Version: 4.1.2
Summary: serial to socket bridge
Home-page: https://github.com/tiagocoutinho/ser2sock/
Author: Jose Tiago Macara Coutinho
Author-email: coutinhotiago@gmail.com
License: GPLv3+
Project-URL: Documentation, https://tiagocoutinho.github.io/ser2sock/
Project-URL: Source, https://github.com/tiagocoutinho/ser2sock/
Keywords: serial line,tcp,udp,bridge,socket,server
Platform: UNKNOWN
Classifier: Development Status :: 2 - Pre-Alpha
Classifier: Intended Audience :: Developers
Classifier: Natural Language :: English
Classifier: Programming Language :: Python :: 2.6
Classifier: Programming Language :: Python :: 2.7
Classifier: Programming Language :: Python :: 3
Classifier: Programming Language :: Python :: 3.4
Classifier: Programming Language :: Python :: 3.5
Classifier: Programming Language :: Python :: 3.6
Classifier: Programming Language :: Python :: 3.7
Classifier: Programming Language :: Python :: 3.8
Classifier: Programming Language :: Python :: 3.9
Classifier: Programming Language :: Python :: 3.10
Classifier: Programming Language :: Python :: 3.11
Requires-Python: >=2.6
Provides-Extra: web
